ezconfigurator/Config.py
ezconfigurator/__init__.py
ezconfigurator-0.0.4.dist-info/LICENSE
ezconfigurator-0.0.4.dist-info/METADATA
ezconfigurator-0.0.4.dist-info/WHEEL
ezconfigurator-0.0.4.dist-info/top_level.txt
ezconfigurator-0.0.4.dist-info/RECORD
