Metadata-Version: 2.1
Name: ezconfigurator
Version: 0.0.4
Summary: A small package to read config json files
Home-page: https://gitlab.com/justin-guth.de/config
Author: justin-guth.de
Author-email: ezconfigurator@justin-guth.de
Project-URL: Bug Tracker, https://gitlab.com/justin-guth.de/config/-/issues
Classifier: Programming Language :: Python :: 3
Classifier: License :: OSI Approved :: GNU General Public License v3 (GPLv3)
Classifier: Operating System :: OS Independent
Requires-Python: >=3.6
License-File: LICENSE
